<annotation>
	<folder>cr</folder>
	<filename>crazing_47.jpg</filename>
	<source>
		<database>NEU-DET</database>
	</source>
	<size>
		<width>200</width>
		<height>200</height>
		<depth>1</depth>
	</size>
	<segmented>0</segmented>
	<object>
		<name>crazing</name>
		<pose>Unspecified</pose>
		<truncated>1</truncated>
		<difficult>0</difficult>
		<bndbox>
			<xmin>4</xmin>
			<ymin>1</ymin>
			<xmax>105</xmax>
			<ymax>149</ymax>
		</bndbox>
	</object>
	<object>
		<name>crazing</name>
		<pose>Unspecified</pose>
		<truncated>1</truncated>
		<difficult>0</difficult>
		<bndbox>
			<xmin>1</xmin>
			<ymin>151</ymin>
			<xmax>72</xmax>
			<ymax>199</ymax>
		</bndbox>
	</object>
</annotation>
