<annotation>
	<folder>rs</folder>
	<filename>rolled-in_scale_160.jpg</filename>
	<source>
  		 <database>NEU-DET</database>
	</source>
	<size>
		<width>200</width>
		<height>200</height>
		<depth>1</depth>
	</size>
	<segmented>0</segmented>
	<object>
		<name>rolled-in_scale</name>
		<pose>Unspecified</pose>
		<truncated>1</truncated>
		<difficult>0</difficult>
		<bndbox>
			<xmin>43</xmin>
			<ymin>1</ymin>
			<xmax>83</xmax>
			<ymax>73</ymax>
		</bndbox>
	</object>
	<object>
		<name>rolled-in_scale</name>
		<pose>Unspecified</pose>
		<truncated>1</truncated>
		<difficult>0</difficult>
		<bndbox>
			<xmin>39</xmin>
			<ymin>138</ymin>
			<xmax>84</xmax>
			<ymax>200</ymax>
		</bndbox>
	</object>
	<object>
		<name>rolled-in_scale</name>
		<pose>Unspecified</pose>
		<truncated>1</truncated>
		<difficult>0</difficult>
		<bndbox>
			<xmin>100</xmin>
			<ymin>149</ymin>
			<xmax>200</xmax>
			<ymax>200</ymax>
		</bndbox>
	</object>
</annotation>
